django_access_logging/__init__.py
django_access_logging/_access_logging.py
django_access_logging/admin.py
django_access_logging/models.py
django_access_logging/ipware/__init__.py
django_access_logging/ipware/apps.py
django_access_logging/ipware/defaults.py
django_access_logging/ipware/ip.py
django_access_logging/ipware/ip2.py
django_access_logging/ipware/utils.py
django_access_logging/ipware/tests/__init__.py
django_access_logging/ipware/tests/tests_common.py
django_access_logging/ipware/tests/tests_ipv4.py
django_access_logging/ipware/tests/tests_ipv6.py
django_access_logging/ipware/tests/testsettings.py
django_access_logging/ipware/tests/tests_v1/__init__.py
django_access_logging/ipware/tests/tests_v1/tests_ipv4.py
django_access_logging/ipware/tests/tests_v1/tests_ipv6.py
django_access_logging/migrations/0001_initial.py
django_access_logging/migrations/__init__.py
django_access_logging-1.0.1.dist-info/LICENSE
django_access_logging-1.0.1.dist-info/METADATA
django_access_logging-1.0.1.dist-info/WHEEL
django_access_logging-1.0.1.dist-info/top_level.txt
django_access_logging-1.0.1.dist-info/RECORD
