Metadata-Version: 2.2
Name: django-access-logging
Version: 1.0.1
Summary: Django middleware to log all requests and responses to a database.
Home-page: https://github.com/ross-sharma/django-access-logging
Author: Ross Sharma
Author-email: ross@ross-sharma.com
License: MIT
Classifier: License :: OSI Approved :: MIT License
Classifier: Programming Language :: Python :: 3
License-File: LICENSE
Requires-Dist: django
Dynamic: author
Dynamic: author-email
Dynamic: classifier
Dynamic: description
Dynamic: description-content-type
Dynamic: home-page
Dynamic: license
Dynamic: requires-dist
Dynamic: summary
